{"sheets":{"idle":{"file":"idle.png","frames":[{"x":13,"y":32,"w":430,"h":384,"ax":215,"ay":384},{"x":443,"y":32,"w":443,"h":384,"ax":222,"ay":384},{"x":886,"y":33,"w":443,"h":383,"ax":222,"ay":383},{"x":1329,"y":33,"w":309,"h":383,"ax":155,"ay":383},{"x":23,"y":453,"w":420,"h":395,"ax":210,"ay":395},{"x":443,"y":456,"w":443,"h":391,"ax":222,"ay":391},{"x":886,"y":456,"w":443,"h":391,"ax":222,"ay":391},{"x":1329,"y":457,"w":321,"h":390,"ax":161,"ay":390}]},"walk":{"file":"walk.png","frames":[{"x":25,"y":81,"w":379,"h":330,"ax":190,"ay":330},{"x":444,"y":90,"w":442,"h":322,"ax":221,"ay":322},{"x":886,"y":91,"w":443,"h":322,"ax":222,"ay":322},{"x":1329,"y":91,"w":370,"h":323,"ax":185,"ay":323},{"x":34,"y":478,"w":406,"h":316,"ax":203,"ay":316},{"x":454,"y":485,"w":397,"h":310,"ax":199,"ay":310},{"x":891,"y":488,"w":402,"h":313,"ax":201,"ay":313},{"x":1340,"y":480,"w":369,"h":315,"ax":185,"ay":315}]},"attack":{"file":"attack.png","frames":[{"x":65,"y":114,"w":302,"h":311,"ax":151,"ay":311},{"x":454,"y":127,"w":432,"h":298,"ax":216,"ay":298},{"x":886,"y":133,"w":443,"h":292,"ax":222,"ay":292},{"x":1329,"y":151,"w":440,"h":251,"ax":220,"ay":251},{"x":25,"y":513,"w":394,"h":293,"ax":197,"ay":293},{"x":477,"y":504,"w":345,"h":305,"ax":173,"ay":305},{"x":896,"y":505,"w":433,"h":305,"ax":217,"ay":305},{"x":1329,"y":497,"w":283,"h":318,"ax":142,"ay":318}]},"hit":{"file":"hit.png","frames":[{"x":16,"y":34,"w":407,"h":401,"ax":204,"ay":401},{"x":444,"y":86,"w":423,"h":350,"ax":212,"ay":350},{"x":897,"y":130,"w":369,"h":303,"ax":185,"ay":303},{"x":1341,"y":147,"w":364,"h":287,"ax":182,"ay":287},{"x":27,"y":571,"w":365,"h":270,"ax":183,"ay":270},{"x":456,"y":489,"w":372,"h":352,"ax":186,"ay":352},{"x":900,"y":489,"w":429,"h":353,"ax":215,"ay":353},{"x":1329,"y":486,"w":337,"h":356,"ax":169,"ay":356}]},"ko":{"file":"ko.png","frames":[{"x":12,"y":81,"w":424,"h":305,"ax":212,"ay":305},{"x":452,"y":107,"w":397,"h":292,"ax":199,"ay":292},{"x":937,"y":116,"w":384,"h":283,"ax":192,"ay":283},{"x":1403,"y":97,"w":349,"h":297,"ax":175,"ay":297},{"x":32,"y":567,"w":388,"h":231,"ax":194,"ay":231},{"x":465,"y":575,"w":388,"h":220,"ax":194,"ay":220},{"x":896,"y":650,"w":425,"h":155,"ax":213,"ay":155},{"x":1346,"y":676,"w":422,"h":145,"ax":211,"ay":145}]},"win":{"file":"win.png","frames":[{"x":31,"y":20,"w":367,"h":378,"ax":184,"ay":378},{"x":539,"y":21,"w":269,"h":377,"ax":135,"ay":377},{"x":966,"y":21,"w":271,"h":422,"ax":136,"ay":422},{"x":1380,"y":20,"w":257,"h":423,"ax":129,"ay":423},{"x":123,"y":455,"w":278,"h":400,"ax":139,"ay":400},{"x":533,"y":446,"w":268,"h":408,"ax":134,"ay":408},{"x":922,"y":443,"w":407,"h":412,"ax":204,"ay":412},{"x":1329,"y":443,"w":290,"h":411,"ax":145,"ay":411}]}},"unitHeight":390}